covidactnow/__init__.py
covidactnow/covid.py
covidactnow-1.1.76.dist-info/METADATA
covidactnow-1.1.76.dist-info/WHEEL
covidactnow-1.1.76.dist-info/top_level.txt
covidactnow-1.1.76.dist-info/RECORD
